logtk/__init__.py
logtk/logger/__init__.py
logtk/logger/objects.py
logtk/logging/__init__.py
logtk/loguru_logger/__init__.py
logtk/loguru_logger/objects.py
logtk-1.0.13.dist-info/WHEEL
logtk-1.0.13.dist-info/METADATA
logtk-1.0.13.dist-info/RECORD
