Metadata-Version: 2.1
Name: logtk
Version: 1.0.13
Summary: logging toolkit
License: MIT
Author: wayfaring-stranger
Author-email: zw6p226m@duck.com
Requires-Python: >=3.9,<4.0
Classifier: License :: OSI Approved :: MIT License
Classifier: Programming Language :: Python :: 3
Classifier: Programming Language :: Python :: 3.9
Classifier: Programming Language :: Python :: 3.10
Classifier: Programming Language :: Python :: 3.11
Requires-Dist: colortk (==1.0.0)
Requires-Dist: loguru (==0.6.0)
